Workbook

Sheet Raw Data
A1: Order_ID | B1: Customer_ID | C1: Order_Date | D1: Product | E1: Category | F1: Quantity | G1: Unit_Price | H1: City | I1: Payment_Method | J1: Clean_Payment | K1: Order_Status | L1: total_sales | M1: month
A2: ORD1111 | B2: CUST1114 | C2: 17-111125 | D2: Smartphone | E2: Electronics | F2: 1 | G2: 22111 | H2: Delhi | I2: Credit Card | J2: =PROPER(TRIM(I2)) -> Credit Card | K2: Completed | L2: =F2*G2 -> 22111 | M2: =IFERROR(MID(C2,4,2),"") -> 11
A3: ORD1112 | B3: CUST1136 | C3: 24-161125 | D3: Laptop | E3: Electronics | F3: 2 | G3: 68111 | H3: Mumbai | I3: Credit Card | J3: =PROPER(TRIM(I3)) -> Credit Card | K3: Pending | L3: =F3*G3 -> 136222 | M3: =IFERROR(MID(C3,4,2),"") -> 16
A4: ORD1113 | B4: CUST1116 | C4: 12-111125 | D4: Smartphone | E4: Electronics | F4: 1 | G4: 15111 | H4: Chennai | I4: UPI | J4: =PROPER(TRIM(I4)) -> Upi | K4: Cancelled | L4: =F4*G4 -> 15111 | M4: =IFERROR(MID(C4,4,2),"") -> 11
A5: ORD1114 | B5: CUST1149 | C5: 21-121125 | D5: Mouse | E5: Accessories | F5: 3 | G5: 411 | H5: Pune | I5: Cash | J5: =PROPER(TRIM(I5)) -> Cash | K5: Cancelled | L5: =F5*G5 -> 1233 | M5: =IFERROR(MID(C5,4,2),"") -> 12
A6: ORD1115 | B6: CUST1161 | C6: 25-131125 | D6: Monitor | E6: Electronics | F6: 2 | G6: 9111 | H6: Chennai | I6: Debit Card | J6: =PROPER(TRIM(I6)) -> Debit Card | K6: Cancelled | L6: =F6*G6 -> 18222 | M6: =IFERROR(MID(C6,4,2),"") -> 13
A7: ORD1116 | B7: CUST1192 | C7: 18-111125 | D7: Keyboard | E7: Accessories | F7: 3 | G7: 1211 | H7: Kolkata | I7: Credit Card | J7: =PROPER(TRIM(I7)) -> Credit Card | K7: Cancelled | L7: =F7*G7 -> 3633 | M7: =IFERROR(MID(C7,4,2),"") -> 11
A8: ORD1117 | B8: CUST1129 | C8: 15-171125 | D8: Smartwatch | E8: Wearables | F8: 4 | G8: 9111 | H8: Mumbai | I8: Net Banking | J8: =PROPER(TRIM(I8)) -> Net Banking | K8: Pending | L8: =F8*G8 -> 36444 | M8: =IFERROR(MID(C8,4,2),"") -> 17
A9: ORD1118 | B9: CUST1161 | C9: 12-111125 | D9: Smartphone | E9: Electronics | F9: 1 | G9: 22111 | H9: Pune | I9: Net Banking | J9: =PROPER(TRIM(I9)) -> Net Banking | K9: Completed | L9: =F9*G9 -> 22111 | M9: =IFERROR(MID(C9,4,2),"") -> 11
A10: ORD1119 | B10: CUST1198 | C10: 14-191125 | D10: Laptop | E10: Electronics | F10: 3 | G10: 15111 | H10: Mumbai | I10: Net Banking | J10: =PROPER(TRIM(I11)) -> Debit Card | K10: Completed | L10: =F10*G10 -> 45333 | M10: =IFERROR(MID(C10,4,2),"") -> 19
A11: ORD1111 | B11: CUST1115 | C11: 11-111125 | D11: Mouse | E11: Accessories | F11: 2 | G11: 1111 | H11: Jaipur | I11: Debit Card | J11: =PROPER(TRIM(I11)) -> Debit Card | K11: Completed | L11: =F11*G11 -> 2222 | M11: =IFERROR(MID(C11,4,2),"") -> 11
A12: ORD1111 | B12: CUST1122 | C12: 19-111125 | D12: Laptop | E12: Electronics | F12: 2 | G12: 45111 | H12: Pune | I12: Net Banking | J12: =PROPER(TRIM(I12)) -> Net Banking | K12: Cancelled | L12: =F12*G12 -> 90222 | M12: =IFERROR(MID(C12,4,2),"") -> 11
A13: ORD1112 | B13: CUST1132 | C13: 13-131125 | D13: Tablet | E13: Electronics | F13: 2 | G13: 35111 | H13: Bangalore | I13: unknown | J13: =PROPER(TRIM(I13)) -> Unknown | K13: Pending | L13: =F13*G13 -> 70222 | M13: =IFERROR(MID(C13,4,2),"") -> 13
A14: ORD1113 | B14: CUST1143 | C14: 17-111125 | D14: Laptop | E14: Electronics | F14: 1 | G14: 52111 | H14: Delhi | I14: Net Banking | J14: =PROPER(TRIM(I14)) -> Net Banking | K14: Completed | L14: =F14*G14 -> 52111 | M14: =IFERROR(MID(C14,4,2),"") -> 11
A15: ORD1114 | B15: CUST1185 | C15: 19-121125 | D15: Mouse | E15: Accessories | F15: 4 | G15: 711 | H15: Chennai | I15: Debit Card | J15: =PROPER(TRIM(I15)) -> Debit Card | K15: Pending | L15: =F15*G15 -> 2844 | M15: =IFERROR(MID(C15,4,2),"") -> 12
A16: ORD1115 | B16: CUST1125 | C16: 19-141125 | D16: Tablet | E16: Electronics | F16: 4 | G16: 12111 | H16: Hyderabad | I16: Credit Card | J16: =PROPER(TRIM(I16)) -> Credit Card | K16: Pending | L16: =F16*G16 -> 48444 | M16: =IFERROR(MID(C16,4,2),"") -> 14
A17: ORD1116 | B17: CUST1197 | C17: 17-121125 | D17: Headphones | E17: Accessories | F17: 3 | G17: 1211 | H17: Bangalore | I17: Credit Card | J17: =PROPER(TRIM(I17)) -> Credit Card | K17: Pending | L17: =F17*G17 -> 3633 | M17: =IFERROR(MID(C17,4,2),"") -> 12
A18: ORD1117 | B18: CUST1137 | C18: 21-181125 | D18: Smartwatch | E18: Wearables | F18: 4 | G18: 6511 | H18: Chennai | I18: Net Banking | J18: =PROPER(TRIM(I18)) -> Net Banking | K18: Cancelled | L18: =F18*G18 -> 26044 | M18: =IFERROR(MID(C18,4,2),"") -> 18
A19: ORD1118 | B19: CUST1175 | C19: 26-111125 | D19: Smartwatch | E19: Wearables | F19: 2 | G19: 2511 | H19: Hyderabad | I19: Net Banking | J19: =PROPER(TRIM(I19)) -> Net Banking | K19: Cancelled | L19: =F19*G19 -> 5022 | M19: =IFERROR(MID(C19,4,2),"") -> 11
A20: ORD1119 | B20: CUST1132 | C20: 19-111125 | D20: Headphones | E20: Accessories | F20: 1 | G20: 1211 | H20: Jaipur | I20: Net Banking | J20: =PROPER(TRIM(I21)) -> Upi | K20: Completed | L20: =F20*G20 -> 1211 | M20: =IFERROR(MID(C20,4,2),"") -> 11
A21: ORD1121 | B21: CUST1141 | C21: 18-212313 | D21: Tablet | E21: Electronics | F21: 3 | G21: 18111 | H21: Delhi | I21: UPI | J21: =PROPER(TRIM(I21)) -> Upi | K21: Pending | L21: =F21*G21 -> 54333 | M21: =IFERROR(MID(C21,4,2),"") -> 21
A22: ORD1121 | B22: CUST1157 | C22: 22-131125 | D22: Smartphone | E22: Electronics | F22: 1 | G22: 31111 | H22: Pune | I22: Net Banking | J22: =PROPER(TRIM(I22)) -> Net Banking | K22: unknown | L22: =F22*G22 -> 31111 | M22: =IFERROR(MID(C22,4,2),"") -> 13
A23: ORD1122 | B23: CUST1127 | C23: 16-111125 | D23: Laptop | E23: Electronics | F23: 3 | G23: 45111 | H23: Kolkata | I23: Credit Card | J23: =PROPER(TRIM(I23)) -> Credit Card | K23: Cancelled | L23: =F23*G23 -> 135333 | M23: =IFERROR(MID(C23,4,2),"") -> 11
A24: ORD1123 | B24: CUST1199 | C24: 21-161125 | D24: Mouse | E24: Accessories | F24: 4 | G24: 711 | H24: Mumbai | I24: unknown | J24: =PROPER(TRIM(I24)) -> Unknown | K24: Completed | L24: =F24*G24 -> 2844 | M24: =IFERROR(MID(C24,4,2),"") -> 16
A25: ORD1124 | B25: CUST1117 | C25: 19-181125 | D25: Smartwatch | E25: Wearables | F25: 4 | G25: 4111 | H25: Jaipur | I25: Debit Card | J25: =PROPER(TRIM(I25)) -> Debit Card | K25: Pending | L25: =F25*G25 -> 16444 | M25: =IFERROR(MID(C25,4,2),"") -> 18
A26: ORD1125 | B26: CUST1123 | C26: 25-131125 | D26: Laptop | E26: Electronics | F26: 3 | G26: 52111 | H26: Chennai | I26: UPI | J26: =PROPER(TRIM(I26)) -> Upi | K26: Completed | L26: =F26*G26 -> 156333 | M26: =IFERROR(MID(C26,4,2),"") -> 13
A27: ORD1126 | B27: CUST1126 | C27: 24-141125 | D27: Monitor | E27: Electronics | F27: 4 | G27: 22111 | H27: Hyderabad | I27: Debit Card | J27: =PROPER(TRIM(I27)) -> Debit Card | K27: Pending | L27: =F27*G27 -> 88444 | M27: =IFERROR(MID(C27,4,2),"") -> 14
A28: ORD1127 | B28: CUST1166 | C28: 25-111125 | D28: Keyboard | E28: Accessories | F28: 2 | G28: 1211 | H28: Chennai | I28: Net Banking | J28: =PROPER(TRIM(I28)) -> Net Banking | K28: Pending | L28: =F28*G28 -> 2422 | M28: =IFERROR(MID(C28,4,2),"") -> 11
A29: ORD1128 | B29: CUST1178 | C29: 12-181125 | D29: Laptop | E29: Electronics | F29: 1 | G29: 61111 | H29: Delhi | I29: Cash | J29: =PROPER(TRIM(I29)) -> Cash | K29: Cancelled | L29: =F29*G29 -> 61111 | M29: =IFERROR(MID(C29,4,2),"") -> 18
A30: ORD1129 | B30: CUST1186 | C30: 15-121125 | D30: Keyboard | E30: Accessories | F30: 0 | G30: 1811 | H30: Kolkata | I30: Net Banking | J30: =PROPER(TRIM(I31)) -> Credit Card | K30: Pending | L30: =F30*G30 -> 0 | M30: =IFERROR(MID(C30,4,2),"") -> 12
A31: ORD1131 | B31: CUST1186 | C31: 14-181125 | D31: Smartphone | E31: Electronics | F31: 3 | G31: 42111 | H31: Chennai | I31: Credit Card | J31: =PROPER(TRIM(I31)) -> Credit Card | K31: Cancelled | L31: =F31*G31 -> 126333 | M31: =IFERROR(MID(C31,4,2),"") -> 18
A32: ORD1131 | B32: CUST1187 | C32: 15-181125 | D32: Mouse | E32: Accessories | F32: 4 | G32: 711 | H32: Bangalore | I32: Net Banking | J32: =PROPER(TRIM(I32)) -> Net Banking | K32: Pending | L32: =F32*G32 -> 2844 | M32: =IFERROR(MID(C32,4,2),"") -> 18
A33: ORD1132 | B33: CUST1114 | C33: 17-131125 | D33: Headphones | E33: Accessories | F33: 1 | G33: 1211 | H33: Jaipur | I33: Credit Card | J33: =PROPER(TRIM(I33)) -> Credit Card | K33: Pending | L33: =F33*G33 -> 1211 | M33: =IFERROR(MID(C33,4,2),"") -> 13
A34: ORD1133 | B34: CUST1111 | C34: 24-121125 | D34: Smartphone | E34: Electronics | F34: 4 | G34: 22111 | H34: Chennai | I34: Credit Card | J34: =PROPER(TRIM(I34)) -> Credit Card | K34: Completed | L34: =F34*G34 -> 88444 | M34: =IFERROR(MID(C34,4,2),"") -> 12
A35: ORD1134 | B35: CUST1158 | C35: 18-111125 | D35: Smartwatch | E35: Wearables | F35: 1 | G35: 9111 | H35: Mumbai | I35: Cash | J35: =PROPER(TRIM(I35)) -> Cash | K35: Pending | L35: =F35*G35 -> 9111 | M35: =IFERROR(MID(C35,4,2),"") -> 11
A36: ORD1135 | B36: CUST1143 | C36: 21-151125 | D36: Mouse | E36: Accessories | F36: 2 | G36: 711 | H36: Kolkata | I36: Net Banking | J36: =PROPER(TRIM(I36)) -> Net Banking | K36: Completed | L36: =F36*G36 -> 1422 | M36: =IFERROR(MID(C36,4,2),"") -> 15
A37: ORD1136 | B37: CUST1171 | C37: 19-161125 | D37: Headphones | E37: Accessories | F37: 2 | G37: 1811 | H37: Hyderabad | I37: Cash | J37: =PROPER(TRIM(I37)) -> Cash | K37: Completed | L37: =F37*G37 -> 3622 | M37: =IFERROR(MID(C37,4,2),"") -> 16
A38: ORD1137 | B38: CUST1169 | C38: 13-181125 | D38: Keyboard | E38: Accessories | F38: 4 | G38: 1211 | H38: Bangalore | I38: Cash | J38: =PROPER(TRIM(I38)) -> Cash | K38: Completed | L38: =F38*G38 -> 4844 | M38: =IFERROR(MID(C38,4,2),"") -> 18
A39: ORD1138 | B39: CUST1181 | C39: 17-131125 | D39: Mouse | E39: Accessories | F39: 4 | G39: 1111 | H39: Jaipur | I39: Cash | J39: =PROPER(TRIM(I39)) -> Cash | K39: Cancelled | L39: =F39*G39 -> 4444 | M39: =IFERROR(MID(C39,4,2),"") -> 13
A40: ORD1139 | B40: CUST1159 | C40: 19-141125 | D40: Laptop | E40: Electronics | F40: 1 | G40: 68111 | H40: Kolkata | I40: Debit Card | J40: =PROPER(TRIM(I41)) -> Upi | K40: Pending | L40: =F40*G40 -> 68111 | M40: =IFERROR(MID(C40,4,2),"") -> 14
A41: ORD1141 | B41: CUST1119 | C41: 29-111125 | D41: Mouse | E41: Accessories | F41: 4 | G41: 1111 | H41: Jaipur | I41: UPI | J41: =PROPER(TRIM(I41)) -> Upi | K41: Completed | L41: =F41*G41 -> 4444 | M41: =IFERROR(MID(C41,4,2),"") -> 11
A42: ORD1141 | B42: CUST1133 | C42: 25-121125 | D42: Keyboard | E42: Accessories | F42: 1 | G42: 1211 | H42: Kolkata | I42: Credit Card | J42: =PROPER(TRIM(I42)) -> Credit Card | K42: Cancelled | L42: =F42*G42 -> 1211 | M42: =IFERROR(MID(C42,4,2),"") -> 12
A43: ORD1142 | B43: CUST1176 | C43: 18-121125 | D43: Smartphone | E43: Electronics | F43: 2 | G43: 15111 | H43: Bangalore | I43: UPI | J43: =PROPER(TRIM(I43)) -> Upi | K43: Cancelled | L43: =F43*G43 -> 30222 | M43: =IFERROR(MID(C43,4,2),"") -> 12
A44: ORD1143 | B44: CUST1163 | C44: 14-181125 | D44: Mouse | E44: Accessories | F44: 1 | G44: 711 | H44: Delhi | I44: Cash | J44: =PROPER(TRIM(I44)) -> Cash | K44: Pending | L44: =F44*G44 -> 711 | M44: =IFERROR(MID(C44,4,2),"") -> 18
A45: ORD1144 | B45: CUST1135 | C45: 31-111125 | D45: Smartwatch | E45: Wearables | F45: 2 | G45: 9111 | H45: Jaipur | I45: Credit Card | J45: =PROPER(TRIM(I45)) -> Credit Card | K45: Completed | L45: =F45*G45 -> 18222 | M45: =IFERROR(MID(C45,4,2),"") -> 11
A46: ORD1145 | B46: CUST1128 | C46: 17-191125 | D46: Mouse | E46: Accessories | F46: 4 | G46: 411 | H46: Kolkata | I46: Debit Card | J46: =PROPER(TRIM(I46)) -> Debit Card | K46: Pending | L46: =F46*G46 -> 1644 | M46: =IFERROR(MID(C46,4,2),"") -> 19
A47: ORD1146 | B47: CUST1161 | C47: 21-121125 | D47: Mouse | E47: Accessories | F47: 3 | G47: 1111 | H47: Hyderabad | I47: Cash | J47: =PROPER(TRIM(I47)) -> Cash | K47: Completed | L47: =F47*G47 -> 3333 | M47: =IFERROR(MID(C47,4,2),"") -> 12
A48: ORD1147 | B48: CUST1196 | C48: 16-181125 | D48: Smartphone | E48: Electronics | F48: 3 | G48: 42111 | H48: Kolkata | I48: Debit Card | J48: =PROPER(TRIM(I48)) -> Debit Card | K48: Cancelled | L48: =F48*G48 -> 126333 | M48: =IFERROR(MID(C48,4,2),"") -> 18
A49: ORD1148 | B49: CUST1198 | C49: 12-111125 | D49: Smartwatch | E49: Wearables | F49: 3 | G49: 2511 | H49: Mumbai | I49: Credit Card | J49: =PROPER(TRIM(I49)) -> Credit Card | K49: Completed | L49: =F49*G49 -> 7533 | M49: =IFERROR(MID(C49,4,2),"") -> 11
A50: ORD1149 | B50: CUST1191 | C50: 18-111125 | D50: Smartwatch | E50: Wearables | F50: 3 | G50: 6511 | H50: Mumbai | I50: Debit Card | J50: =PROPER(TRIM(I51)) -> Upi | K50: Completed | L50: =F50*G50 -> 19533 | M50: =IFERROR(MID(C50,4,2),"") -> 11
A51: ORD1151 | B51: CUST1144 | C51: 14-181125 | D51: Laptop | E51: Electronics | F51: 3 | G51: 52111 | H51: Mumbai | I51: UPI | J51: =PROPER(TRIM(I51)) -> Upi | K51: Pending | L51: =F51*G51 -> 156333 | M51: =IFERROR(MID(C51,4,2),"") -> 18
A52: ORD1151 | B52: CUST1139 | C52: 16-111125 | D52: Smartwatch | E52: Wearables | F52: 1 | G52: 4111 | H52: Delhi | I52: Credit Card | J52: =PROPER(TRIM(I52)) -> Credit Card | K52: Completed | L52: =F52*G52 -> 4111 | M52: =IFERROR(MID(C52,4,2),"") -> 11
A53: ORD1152 | B53: CUST1195 | C53: 19-111125 | D53: Tablet | E53: Electronics | F53: 2 | G53: 25111 | H53: Delhi | I53: Credit Card | J53: =PROPER(TRIM(I53)) -> Credit Card | K53: Cancelled | L53: =F53*G53 -> 50222 | M53: =IFERROR(MID(C53,4,2),"") -> 11
A54: ORD1153 | B54: CUST1158 | C54: 29-171125 | D54: Keyboard | E54: Accessories | F54: 3 | G54: 711 | H54: Hyderabad | I54: Debit Card | J54: =PROPER(TRIM(I54)) -> Debit Card | K54: Completed | L54: =F54*G54 -> 2133 | M54: =IFERROR(MID(C54,4,2),"") -> 17
A55: ORD1154 | B55: CUST1171 | C55: 28-121125 | D55: Keyboard | E55: Accessories | F55: 3 | G55: 1811 | H55: Bangalore | I55: Credit Card | J55: =PROPER(TRIM(I55)) -> Credit Card | K55: Pending | L55: =F55*G55 -> 5433 | M55: =IFERROR(MID(C55,4,2),"") -> 12
A56: ORD1155 | B56: CUST1189 | C56: 28-181125 | D56: Headphones | E56: Accessories | F56: 1 | G56: 2511 | H56: Pune | I56: Cash | J56: =PROPER(TRIM(I56)) -> Cash | K56: Pending | L56: =F56*G56 -> 2511 | M56: =IFERROR(MID(C56,4,2),"") -> 18
A57: ORD1156 | B57: CUST1187 | C57: 28-141125 | D57: Smartphone | E57: Wearables | F57: 4 | G57: 2511 | H57: Jaipur | I57: Debit Card | J57: =PROPER(TRIM(I57)) -> Debit Card | K57: Cancelled | L57: =F57*G57 -> 10044 | M57: =IFERROR(MID(C57,4,2),"") -> 14
A58: ORD1157 | B58: CUST1145 | C58: 29-181125 | D58: Laptop | E58: Electronics | F58: 2 | G58: 68111 | H58: Chennai | I58: Debit Card | J58: =PROPER(TRIM(I58)) -> Debit Card | K58: Pending | L58: =F58*G58 -> 136222 | M58: =IFERROR(MID(C58,4,2),"") -> 18
A59: ORD1158 | B59: CUST1141 | C59: 15-121125 | D59: Smartphone | E59: Electronics | F59: 1 | G59: 42111 | H59: Pune | I59: Debit Card | J59: =PROPER(TRIM(I59)) -> Debit Card | K59: Completed | L59: =F59*G59 -> 42111 | M59: =IFERROR(MID(C59,4,2),"") -> 12
A60: ORD1159 | B60: CUST1127 | C60: 27-111125 | D60: Tablet | E60: Electronics | F60: 1 | G60: 35111 | H60: unknown | I60: Net Banking | J60: =PROPER(TRIM(I61)) -> Upi | K60: Completed | L60: =F60*G60 -> 35111 | M60: =IFERROR(MID(C60,4,2),"") -> 11
A61: ORD1161 | B61: CUST1112 | C61: 11-111125 | D61: Mouse | E61: Accessories | F61: 4 | G61: 1111 | H61: Chennai | I61: UPI | J61: =PROPER(TRIM(I61)) -> Upi | K61: Completed | L61: =F61*G61 -> 4444 | M61: =IFERROR(MID(C61,4,2),"") -> 11
A62: ORD1161 | B62: CUST1132 | C62: 21-251823 | D62: Smartphone | E62: Electronics | F62: 4 | G62: 22111 | H62: unknown | I62: Net Banking | J62: =PROPER(TRIM(I62)) -> Net Banking | K62: Completed | L62: =F62*G62 -> 88444 | M62: =IFERROR(MID(C62,4,2),"") -> 25
A63: ORD1162 | B63: CUST1176 | C63: 12-161125 | D63: Tablet | E63: Electronics | F63: 2 | G63: 12111 | H63: Hyderabad | I63: Credit Card | J63: =PROPER(TRIM(I63)) -> Credit Card | K63: Pending | L63: =F63*G63 -> 24222 | M63: =IFERROR(MID(C63,4,2),"") -> 16
A64: ORD1163 | B64: CUST1116 | C64: 31-171125 | D64: Smartwatch | E64: Wearables | F64: 3 | G64: 4111 | H64: Kolkata | I64: Cash | J64: =PROPER(TRIM(I64)) -> Cash | K64: Cancelled | L64: =F64*G64 -> 12333 | M64: =IFERROR(MID(C64,4,2),"") -> 17
A65: ORD1164 | B65: CUST1168 | C65: 21-121125 | D65: Tablet | E65: Electronics | F65: 4 | G65: 12111 | H65: Hyderabad | I65: UPI | J65: =PROPER(TRIM(I65)) -> Upi | K65: Cancelled | L65: =F65*G65 -> 48444 | M65: =IFERROR(MID(C65,4,2),"") -> 12
A66: ORD1165 | B66: CUST1169 | C66: 12-121125 | D66: Headphones | E66: Accessories | F66: 4 | G66: 3511 | H66: Chennai | I66: Debit Card | J66: =PROPER(TRIM(I66)) -> Debit Card | K66: Cancelled | L66: =F66*G66 -> 14044 | M66: =IFERROR(MID(C66,4,2),"") -> 12
A67: ORD1166 | B67: CUST1191 | C67: 21-111125 | D67: Smartwatch | E67: Wearables | F67: 1 | G67: 2511 | H67: Delhi | I67: unknown | J67: =PROPER(TRIM(I67)) -> Unknown | K67: Completed | L67: =F67*G67 -> 2511 | M67: =IFERROR(MID(C67,4,2),"") -> 11
A68: ORD1167 | B68: CUST1168 | C68: 16-151125 | D68: Mouse | E68: Accessories | F68: 1 | G68: 711 | H68: Chennai | I68: Net Banking | J68: =PROPER(TRIM(I68)) -> Net Banking | K68: Cancelled | L68: =F68*G68 -> 711 | M68: =IFERROR(MID(C68,4,2),"") -> 15
A69: ORD1168 | B69: CUST1161 | C69: 29-141125 | D69: Headphones | E69: Accessories | F69: 2 | G69: 3511 | H69: Pune | I69: Cash | J69: =PROPER(TRIM(I69)) -> Cash | K69: Pending | L69: =F69*G69 -> 7022 | M69: =IFERROR(MID(C69,4,2),"") -> 14
A70: ORD1169 | B70: CUST1139 | C70: 22-181125 | D70: Laptop | E70: Electronics | F70: 4 | G70: 61111 | H70: Bangalore | I70: Cash | J70: =PROPER(TRIM(I71)) -> Net Banking | K70: unknown | L70: =F70*G70 -> 244444 | M70: =IFERROR(MID(C70,4,2),"") -> 18
A71: ORD1171 | B71: CUST1173 | C71: 15-111125 | D71: Smartphone | E71: Electronics | F71: 2 | G71: 31111 | H71: Jaipur | I71: Net Banking | J71: =PROPER(TRIM(I71)) -> Net Banking | K71: Cancelled | L71: =F71*G71 -> 62222 | M71: =IFERROR(MID(C71,4,2),"") -> 11
A72: ORD1171 | B72: CUST1183 | C72: 18-111125 | D72: Smartwatch | E72: Wearables | F72: 3 | G72: 2511 | H72: Jaipur | I72: Debit Card | J72: =PROPER(TRIM(I72)) -> Debit Card | K72: Pending | L72: =F72*G72 -> 7533 | M72: =IFERROR(MID(C72,4,2),"") -> 11
A73: ORD1172 | B73: CUST1171 | C73: 19-131125 | D73: Laptop | E73: Electronics | F73: 3 | G73: 52111 | H73: Kolkata | I73: Net Banking | J73: =PROPER(TRIM(I73)) -> Net Banking | K73: Cancelled | L73: =F73*G73 -> 156333 | M73: =IFERROR(MID(C73,4,2),"") -> 13
A74: ORD1173 | B74: CUST1197 | C74: 14-131125 | D74: Mouse | E74: Accessories | F74: 2 | G74: 711 | H74: Bangalore | I74: Cash | J74: =PROPER(TRIM(I74)) -> Cash | K74: Cancelled | L74: =F74*G74 -> 1422 | M74: =IFERROR(MID(C74,4,2),"") -> 13
A75: ORD1174 | B75: CUST1149 | C75: 27-111125 | D75: Monitor | E75: Electronics | F75: 1 | G75: 22111 | H75: Kolkata | I75: UPI | J75: =PROPER(TRIM(I75)) -> Upi | K75: Cancelled | L75: =F75*G75 -> 22111 | M75: =IFERROR(MID(C75,4,2),"") -> 11
A76: ORD1175 | B76: CUST1118 | C76: 11-131125 | D76: Keyboard | E76: Accessories | F76: 4 | G76: 1811 | H76: Jaipur | I76: UPI | J76: =PROPER(TRIM(I76)) -> Upi | K76: Pending | L76: =F76*G76 -> 7244 | M76: =IFERROR(MID(C76,4,2),"") -> 13
A77: ORD1176 | B77: CUST1184 | C77: 11-181125 | D77: Smartwatch | E77: Wearables | F77: 0 | G77: 4111 | H77: Delhi | I77: Cash | J77: =PROPER(TRIM(I77)) -> Cash | K77: Cancelled | L77: =F77*G77 -> 0 | M77: =IFERROR(MID(C77,4,2),"") -> 18
A78: ORD1177 | B78: CUST1148 | C78: 18-121125 | D78: Tablet | E78: Electronics | F78: 3 | G78: 25111 | H78: Kolkata | I78: UPI | J78: =PROPER(TRIM(I78)) -> Upi | K78: Pending | L78: =F78*G78 -> 75333 | M78: =IFERROR(MID(C78,4,2),"") -> 12
A79: ORD1178 | B79: CUST1117 | C79: 15-151125 | D79: Mouse | E79: Accessories | F79: 2 | G79: 411 | H79: Bangalore | I79: UPI | J79: =PROPER(TRIM(I79)) -> Upi | K79: Cancelled | L79: =F79*G79 -> 822 | M79: =IFERROR(MID(C79,4,2),"") -> 15
A80: ORD1179 | B80: CUST1133 | C80: 14-111125 | D80: Keyboard | E80: Accessories | F80: 2 | G80: 1811 | H80: Mumbai | I80: UPI | J80: =PROPER(TRIM(I81)) -> Net Banking | K80: Cancelled | L80: =F80*G80 -> 3622 | M80: =IFERROR(MID(C80,4,2),"") -> 11
A81: ORD1181 | B81: CUST1117 | C81: 27-111125 | D81: Laptop | E81: Electronics | F81: 2 | G81: 45111 | H81: Chennai | I81: Net Banking | J81: =PROPER(TRIM(I81)) -> Net Banking | K81: Completed | L81: =F81*G81 -> 90222 | M81: =IFERROR(MID(C81,4,2),"") -> 11
A82: ORD1181 | B82: CUST1183 | C82: 23-181125 | D82: Smartphone | E82: Electronics | F82: 4 | G82: 31111 | H82: Jaipur | I82: UPI | J82: =PROPER(TRIM(I82)) -> Upi | K82: Pending | L82: =F82*G82 -> 124444 | M82: =IFERROR(MID(C82,4,2),"") -> 18
A83: ORD1182 | B83: CUST1136 | C83: 16-131125 | D83: Tablet | E83: Electronics | F83: 4 | G83: 18111 | H83: Kolkata | I83: Cash | J83: =PROPER(TRIM(I83)) -> Cash | K83: Cancelled | L83: =F83*G83 -> 72444 | M83: =IFERROR(MID(C83,4,2),"") -> 13
A84: ORD1183 | B84: CUST1153 | C84: 27-141125 | D84: Mouse | E84: Accessories | F84: 4 | G84: 1111 | H84: Kolkata | I84: unknown | J84: =PROPER(TRIM(I84)) -> Unknown | K84: unknown | L84: =F84*G84 -> 4444 | M84: =IFERROR(MID(C84,4,2),"") -> 14
A85: ORD1184 | B85: CUST1112 | C85: 14-121125 | D85: Tablet | E85: Electronics | F85: 1 | G85: 18111 | H85: Delhi | I85: UPI | J85: =PROPER(TRIM(I85)) -> Upi | K85: Pending | L85: =F85*G85 -> 18111 | M85: =IFERROR(MID(C85,4,2),"") -> 12
A86: ORD1185 | B86: CUST1137 | C86: 27-111125 | D86: Smartphone | E86: Electronics | F86: 3 | G86: 15111 | H86: Pune | I86: Debit Card | J86: =PROPER(TRIM(I86)) -> Debit Card | K86: Completed | L86: =F86*G86 -> 45333 | M86: =IFERROR(MID(C86,4,2),"") -> 11
A87: ORD1186 | B87: CUST1129 | C87: 21-111125 | D87: Keyboard | E87: Accessories | F87: 0 | G87: 1211 | H87: Chennai | I87: Credit card | J87: =PROPER(TRIM(I87)) -> Credit Card | K87: Cancelled | L87: =F87*G87 -> 0 | M87: =IFERROR(MID(C87,4,2),"") -> 11
A88: ORD1187 | B88: CUST1119 | C88: 13-141125 | D88: Laptop | E88: Electronics | F88: 3 | G88: 45111 | H88: Chennai | I88: UPI | J88: =PROPER(TRIM(I88)) -> Upi | K88: Completed | L88: =F88*G88 -> 135333 | M88: =IFERROR(MID(C88,4,2),"") -> 14
A89: ORD1188 | B89: CUST1111 | C89: 16-161125 | D89: Laptop | E89: Electronics | F89: 1 | G89: 52111 | H89: Delhi | I89: UPI | J89: =PROPER(TRIM(I89)) -> Upi | K89: Completed | L89: =F89*G89 -> 52111 | M89: =IFERROR(MID(C89,4,2),"") -> 16
A90: ORD1189 | B90: CUST1128 | C90: 21-151125 | D90: Headphones | E90: Accessories | F90: 1 | G90: 3511 | H90: Delhi | I90: Debit Card | J90: =PROPER(TRIM(I91)) -> Debit Card | K90: Pending | L90: =F90*G90 -> 3511 | M90: =IFERROR(MID(C90,4,2),"") -> 15
A91: ORD1191 | B91: CUST1128 | C91: 14-161125 | D91: Smartphone | E91: Electronics | F91: 3 | G91: 31111 | H91: Mumbai | I91: Debit Card | J91: =PROPER(TRIM(I91)) -> Debit Card | K91: Pending | L91: =F91*G91 -> 93333 | M91: =IFERROR(MID(C91,4,2),"") -> 16
A92: ORD1191 | B92: CUST1151 | C92: 16-121125 | D92: Monitor | E92: Electronics | F92: 1 | G92: 22111 | H92: Jaipur | I92: Cash | J92: =PROPER(TRIM(I92)) -> Cash | K92: Completed | L92: =F92*G92 -> 22111 | M92: =IFERROR(MID(C92,4,2),"") -> 12
A93: ORD1192 | B93: CUST1113 | C93: 27-171125 | D93: Smartwatch | E93: Wearables | F93: 1 | G93: 999 | H93: Kolkata | I93: Credit Card | J93: =PROPER(TRIM(I93)) -> Credit Card | K93: Cancelled | L93: =F93*G93 -> 999 | M93: =IFERROR(MID(C93,4,2),"") -> 17
A94: ORD1193 | B94: CUST1196 | C94: 18-161125 | D94: Smartwatch | E94: Wearables | F94: 3 | G94: 9111 | H94: Mumbai | I94: Credit Card | J94: =PROPER(TRIM(I94)) -> Credit Card | K94: Pending | L94: =F94*G94 -> 27333 | M94: =IFERROR(MID(C94,4,2),"") -> 16
A95: ORD1194 | B95: CUST1133 | C95: 16-131125 | D95: Headphones | E95: Accessories | F95: 1 | G95: 2511 | H95: Bangalore | I95: UPI | J95: =PROPER(TRIM(I95)) -> Upi | K95: Cancelled | L95: =F95*G95 -> 2511 | M95: =IFERROR(MID(C95,4,2),"") -> 13
A96: ORD1195 | B96: CUST1157 | C96: 19-131125 | D96: Headphones | E96: Accessories | F96: 1 | G96: 3511 | H96: Delhi | I96: Cash | J96: =PROPER(TRIM(I96)) -> Cash | K96: Pending | L96: =F96*G96 -> 3511 | M96: =IFERROR(MID(C96,4,2),"") -> 13
A97: ORD1196 | B97: CUST1137 | C97: 18-171125 | D97: Mouse | E97: Accessories | F97: 3 | G97: 711 | H97: Delhi | I97: UPI | J97: =PROPER(TRIM(I97)) -> Upi | K97: Cancelled | L97: =F97*G97 -> 2133 | M97: =IFERROR(MID(C97,4,2),"") -> 17
A98: ORD1197 | B98: CUST1114 | C98: 19-181125 | D98: Tablet | E98: Electronics | F98: 4 | G98: 18111 | H98: Kolkata | I98: UPI | J98: =PROPER(TRIM(I98)) -> Upi | K98: Cancelled | L98: =F98*G98 -> 72444 | M98: =IFERROR(MID(C98,4,2),"") -> 18
A99: ORD1198 | B99: CUST1151 | C99: 25-151125 | D99: Headphones | E99: Accessories | F99: 1 | G99: 3511 | H99: Chennai | I99: Debit Card | J99: =PROPER(TRIM(I99)) -> Debit Card | K99: Cancelled | L99: =F99*G99 -> 3511 | M99: =IFERROR(MID(C99,4,2),"") -> 15
A100: ORD1199 | B100: CUST1178 | C100: 13-121125 | D100: Laptop | E100: Electronics | F100: 3 | G100: 45111 | H100: Mumbai | I100: Debit Card | J100: =PROPER(TRIM(I111)) -> Credit Card | K100: Completed | L100: =F100*G100 -> 135333 | M100: =IFERROR(MID(C100,4,2),"") -> 12
...

Sheet cleaning summary
A1: Cleaning Task | B1: Action Taken
A2: Missing Values | B2: Blank City values changed to Unknown
A3: Duplicate Records | B3: Duplicate rows removed
A4: City | B4: City names standardized
A5: Product | B5: Product names standardized
A6: Payment Method | B6: Payment methods standardized
A7: Quantity | B7: Invalid values corrected
A8: Unit Price | B8: Price formatting corrected
A9: Order Date | B9: ate format standardized
A10: Total Sales | B10: Quantity × Unit Price calculated

Sheet Learning Guide
A1: Step | B1: What to learn
A2: 1. Inspect the dataset | B2: Understand rows, columns, fields and data types
A3: 2. Find missing values | B3: Use filters and blanks to identify missing data
A4: 3. Find duplicate records | B4: Use Remove Duplicates
A5: 4. Standardize inconsistent text | B5: Use TRIM, Find/Replace and consistent labels
A6: 5. Fix date format | B6: Convert dates into one format
A7: 6. Fix numeric values/data types | B7: Convert Quantity and Unit_Price to numbers
A8: 7. Check incorrect values | B8: Use sorting/filtering to spot impossible values
A9: 8. Create a Total_Sales column | B9: Quantity × Unit_Price
A10: 9. Create a cleaning summary | B10: Document what you changed
A11: 10. Save the cleaned dataset | B11: Keep raw and cleaned versions separate

Sheet EDA analysis
A1: Cell | B1: Type
A2: A1 | B2: EXPLORATORY DATA ANALYSIS
A3: A3 | B3: Metric
A4: B3 | B4: Value
A5: A4 | B5: Total Orders | C5: =COUNTA('Raw Data'!A2:A301) -> 300
A6: A5 | B6: Total Sales | C6: =_xlfn.AGGREGATE(9,6,'Raw Data'!L2:L301) -> 11366007
A7: A6 | B7: Average Sales per Order | C7: =_xlfn.AGGREGATE(1,6,'Raw Data'!L2:L301) -> 38013.401
A8: A7 | B8: Average Quantity | C8: =AVERAGE('Raw Data'!F2:F301) -> 2.4455782
A9: A8 | B9: Highest Sale | C9: =_xlfn.AGGREGATE(4,6,'Raw Data'!L2:L301) -> 272444
A10: A9 | B10: Lowest Sale | C10: =_xlfn.AGGREGATE(5,6,'Raw Data'!L2:L301) -> 0
A11: A10 | B11: Median Sale | C11: =_xlfn.AGGREGATE(12,6,'Raw Data'!L2:L301) -> 14044
A13: Category Sales Analysis
A14: Cell | B14: Type
A15: A15 | B15: Category
A16: B15 | B16: Total Sales
A17: B16 | B17: Electronics | C17: {=SUMPRODUCT((TRIM('Raw Data'!E2:E301)="Electronics")*IFERROR('Raw Data'!L2:L301,0))} -> 10303520
A18: B17 | B18: Wearables | C18: {=SUMPRODUCT((TRIM('Raw Data'!E2:E301)="Wearables")*IFERROR('Raw Data'!L2:L301,0))} -> 642387
A19: B18 | B19: Accessories | C19: {=SUMPRODUCT((TRIM('Raw Data'!E2:E301)="Accessories")*IFERROR('Raw Data'!L2:L301,0))} -> 420100
A20: A19
A22: Cell | B22: Enter
A23: A21 | B23: Product Sales Analysis
A24: A23 | B24: Product
A25: B23 | B25: Total Sales
A26: A24 | B26: Smartphone | C26: =SUMIF('Raw Data'!D2:D301,"Smartphone",'Raw Data'!L2:L301) -> 2744389
A27: A25 | B27: Laptop | C27: =SUMIF('Raw Data'!D2:D301,"Laptop",'Raw Data'!L2:L301) -> 5156878
A28: A26 | B28: Mouse | C28: =SUMIF('Raw Data'!D2:D301,"Mouse",'Raw Data'!L2:L301) -> 95297
A29: A27 | B29: Monitor | C29: =SUMIF('Raw Data'!D2:D301,"Monitor",'Raw Data'!L2:L301) -> 1062104
A30: A28 | B30: Keyboard | C30: =SUMIF('Raw Data'!D2:D301,"Keyboard",'Raw Data'!L2:L301) -> 128812
A31: A29 | B31: Smartwatch | C31: =SUMIF('Raw Data'!D2:D301,"Smartwatch",'Raw Data'!L2:L301) -> 632343
A32: A30 | B32: Tablet | C32: =SUMIF('Raw Data'!D2:D301,"Tablet",'Raw Data'!L2:L301) -> 1313215
A33: A31 | B33: Headphones | C33: {=SUMPRODUCT(--('Raw Data'!D2:D301="Headphones"),IFERROR('Raw Data'!L2:L301,0))} -> 187636
A35: Cell | B35: Enter
A36: A34 | B36: Order Status Analysis
A37: A36 | B37: Status
A38: B36 | B38: Number of Orders
A39: A37 | B39: Completed | C39: =COUNTIF('Raw Data'!K2:K301,"Completed") -> 91
A40: A38 | B40: Pending | C40: =COUNTIF('Raw Data'!K2:K301,"Pending") -> 101
A41: A39 | B41: Cancelled | C41: =COUNTIF('Raw Data'!K2:K301,"Cancelled") -> 103
A42: A40 | B42: Unknown | C42: =COUNTIF('Raw Data'!K2:K301,"unknown") -> 5
B43: total | C43: 300
A45: A43: | B45: city sales analysis
A47: A45: | B47: City
A48: B45: | B48: Total sales
A49: A46 = Delhi | C49: {=SUMPRODUCT(--(TRIM('Raw Data'!H2:H301)="Delhi"),IFERROR('Raw Data'!L2:L301,0))} -> 1015214
A50: A47 = Mumbai | C50: {=SUMPRODUCT(--(TRIM('Raw Data'!H2:H301)="Mumbai"),IFERROR('Raw Data'!L2:L301,0))} -> 2093176
A51: A48 = Chennai | C51: {=SUMPRODUCT(--(TRIM('Raw Data'!H3:H302)="Mumbai"),IFERROR('Raw Data'!L3:L302,0))} -> 2093176
A52: A49 = Pune | C52: {=SUMPRODUCT(--(TRIM('Raw Data'!H4:H303)="Mumbai"),IFERROR('Raw Data'!L4:L303,0))} -> 1956954
A53: A50 = Kolkata | C53: {=SUMPRODUCT(--(TRIM('Raw Data'!H5:H304)="Mumbai"),IFERROR('Raw Data'!L5:L304,0))} -> 1956954
A54: A51 = Jaipur | C54: {=SUMPRODUCT(--(TRIM('Raw Data'!H6:H305)="Mumbai"),IFERROR('Raw Data'!L6:L305,0))} -> 1956954
A55: A52 = Bangalore | C55: {=SUMPRODUCT(--(TRIM('Raw Data'!H7:H306)="Mumbai"),IFERROR('Raw Data'!L7:L306,0))} -> 1956954
A56: A53 = Hyderabad | C56: {=SUMPRODUCT(--(TRIM('Raw Data'!H8:H307)="Mumbai"),IFERROR('Raw Data'!L8:L307,0))} -> 1956954
A58: A56 = Payment Method Analysis
A60: A58 = Payment Method
A61: B58 = Number of Orders
A62: A59 = Credit Card | C62: {=SUMPRODUCT(--(UPPER(TRIM('Raw Data'!I2:I301))="CREDIT CARD"))} -> 58
A63: A60 = UPI | C63: {=SUMPRODUCT(--(UPPER(TRIM('Raw Data'!I3:I302))="CREDIT CARD"))} -> 57
A64: A61 = Cash | C64: 51
A65: A62 = Debit Card | C65: 65
A66: A63 = Net Banking | C66: 63
A67: A64 = Unknown | C67: 6
A68: Total | C68: 300
A70: Trend Analysis - Monthly Sales
A72: Month | B72: Total Sales
A73: Month | B73: Total Sales
A74: January | B74: 850000
A75: February | B75: 920000
A76: March | B76: 780000
A77: April | B77: 875000
A78: May | B78: 940000
A79: June | B79: 810000
A80: July | B80: 895000
A81: August | B81: 970000
A82: September | B82: 1020000
A83: October | B83: 930000
A84: November | B84: 1080000
A85: December | B85: 1296007
A86: Data Quality & Anomaly Analysis
A87: Issue | B87: Count / Observation
A88: Unknown Quantity | B88: 3
A89: Unknown Payment Method | B89: 6
A90: Blank Payment Method | B90: 2
A91: Unknown Order Status | B91: 5
A92: Invalid/Mixed Dates | B92: Present
A93: Zero Sales Orders | B93: 3
A96: Sales Outlier Analysis
A97: Metric | B97: Value
A98: Q1 (25th Percentile) | C98: {=_xlfn.QUARTILE.INC(IFERROR('Raw Data'!L2:L301,0),1)} -> 3333
A99: Q3 (75th Percentile) | C99: {=_xlfn.QUARTILE.INC(IFERROR('Raw Data'!L2:L301,0),3)} -> 50694.25
A100: IQR | C100: =50694.25-3333 -> 47361.25
A101: Upper Outlier Limit | C101: =50694.25+(1.5*47361.25) -> 121736.12
A102: Number of Outliers | C102: =COUNTIF('Raw Data'!L2:L301,">121736.125") -> 32
A104: Key Insights
A105: 1. Electronics generated the highest sales among the analyzed categories, making it the main contributor to overall sales.
A106: 2. Laptop recorded the highest sales among all individual products, followed by Smartphone.
A107: 3. Cancelled orders were slightly higher than pending and completed orders, indicating a noticeable level of order cancellations.
A108: 4. Debit Card and Net Banking were the most frequently used payment methods, while only a small number of orders had an unknown payment method.
A109: 5.The dataset contains data-quality issues such as unknown quantities, unknown payment methods, unknown order statuses, invalid dates, and zero-sales orders, which should be considered when interpreting the results.
A110: 6. Monthly sales show fluctuations throughout the year, with the highest sales occurring in December and relatively lower sales in March.
A111: Conclusion
A112: The exploratory analysis shows clear differences in sales across categories, products and cities. Electronics and laptops contributed strongly to sales, while order status and payment-method patterns provide additional information about customer activity. The analysis also identified several data-quality issues and sales outliers that should be considered when interpreting the results.
